asetools-0.1.1.dist-info/METADATA
asetools-0.1.1.dist-info/WHEEL
asetools-0.1.1.dist-info/entry_points.txt
asetools-0.1.1.dist-info/licenses/LICENSE
asetools/__init__.py
asetools/aseinfo.py
asetools/aseprite.py
asetools/asesplit.py
asetools/imageops.py
asetools-0.1.1.dist-info/RECORD
