Metadata-Version: 2.1
Name: asetools
Version: 0.1.1
Summary: Tools to work with Aseprite files
Keywords: aseprite,image,conversion
Author-Email: Aurelien Gateau <mail@agateau.com>
License: Apache 2.0
Classifier: Development Status :: 4 - Beta
Classifier: Environment :: Console
Classifier: Intended Audience :: Developers
Project-URL: Homepage, https://gitlab.com/agateau/asetools
Project-URL: Repository, https://gitlab.com/agateau/asetools
Requires-Python: >=3.9
Requires-Dist: Pillow==10.0.1
Requires-Dist: pypng==0.0.20
